Metadata-Version: 2.1
Name: mode-ng
Version: 0.6.1
Summary: AsyncIO Service-based programming.
Author-email: Ask Solem <ask@celeryproject.org>
Maintainer-email: Lanqing Huang <lqhuang@outlook.com>
License: BSD 3-Clause License
Project-URL: homepage, https://github.com/lqhuang/mode-ng
Keywords: asyncio,service,bootsteps,graph,coroutine,actor
Classifier: Development Status :: 4 - Beta
Classifier: License :: OSI Approved :: BSD License
Classifier: Programming Language :: Python :: 3 :: Only
Classifier: Programming Language :: Python :: 3.10
Classifier: Programming Language :: Python :: 3.11
Classifier: Programming Language :: Python :: Implementation :: CPython
Classifier: Operating System :: POSIX
Classifier: Operating System :: Microsoft :: Windows
Classifier: Operating System :: MacOS :: MacOS X
Classifier: Operating System :: Unix
Classifier: Environment :: No Input/Output (Daemon)
Classifier: Framework :: AsyncIO
Classifier: Intended Audience :: Developers
Requires-Python: >=3.10
License-File: LICENSE
License-File: AUTHORS
Requires-Dist: colorlog (>=2.9.0)
Requires-Dist: croniter (>=0.3.16)
Requires-Dist: mypy-extensions
Provides-Extra: eventlet
Requires-Dist: aioeventlet (~=0.5.1) ; extra == 'eventlet'
Requires-Dist: dnspython ; extra == 'eventlet'
Provides-Extra: gevent
Requires-Dist: aiogevent (~=0.2) ; extra == 'gevent'
Provides-Extra: uvloop
Requires-Dist: uvloop (>=0.8.1) ; extra == 'uvloop'
